agridable/__init__.py
agridable/agridable/__init__.py
agridable/agridable/agridable.py
agridable/assets/__init__.py
agridable/assets/dashAgGridComponentFunctions.js
agridable/assets/dashAgGridCss.css
agridable/assets/dashAgGridFunctions.js
agridable/formats/__init__.py
agridable/formats/_base.py
agridable/formats/cell/__init__.py
agridable/formats/cell/_base.py
agridable/formats/cell/align.py
agridable/formats/cell/border.py
agridable/formats/conditional/__init__.py
agridable/formats/conditional/_base.py
agridable/formats/conditional/continuous_colour.py
agridable/formats/conditional/discrete_colour.py
agridable/formats/grid/__init__.py
agridable/formats/grid/_base.py
agridable/formats/grid/pin.py
agridable/formats/grid/width.py
agridable/formats/value/__init__.py
agridable/formats/value/_base.py
agridable/formats/value/currency.py
agridable/formats/value/duration.py
agridable/formats/value/image.py
agridable/formats/value/number.py
agridable/formats/value/percentage.py
agridable/formats/value/url.py
agridable/formatters/__init__.py
agridable/formatters/_base.py
agridable/formatters/column_formatter.py
agridable/formatters/conditional_column_formatter.py
agridable/formatters/row_formatter.py
agridable-0.0.4.dist-info/LICENSE
agridable-0.0.4.dist-info/METADATA
agridable-0.0.4.dist-info/WHEEL
agridable-0.0.4.dist-info/top_level.txt
agridable-0.0.4.dist-info/RECORD
